beritaterkini/__init__.py
latestnews_kemendikbud-0.0.3.dist-info/LICENSE
latestnews_kemendikbud-0.0.3.dist-info/METADATA
latestnews_kemendikbud-0.0.3.dist-info/WHEEL
latestnews_kemendikbud-0.0.3.dist-info/top_level.txt
latestnews_kemendikbud-0.0.3.dist-info/RECORD
